{"singlePage": ["about", "link"], "startSite": "04/18/2024", "filingNum": "", "onePageListNum": 50, "commentLabelColor": "#006b75", "yearColorList": ["#bc4c00", "#0969da", "#1f883d", "#A333D0"], "i18n": "CN", "themeMode": "manual", "dayTheme": "light", "nightTheme": "dark", "urlMode": "pinyin", "script": "", "style": "", "bottomText": "\u8fd9\u91cc\u624d\u662f\u4f60\u7684\u5f00\u59cb", "showPostSource": 1, "iconList": {}, "UTC": 8, "rssSplit": "$$$$$$$", "exlink": {}, "title": "\u4e00\u767e\u5e74\u540e\u518d\u89c1", "subTitle": "\u535a\u5ba2\u2014\u2014\u8bb0\u5f55\u70b9\u70b9\u6ef4\u6ef4", "homeUrl": "https://blog.00002000.xyz", "avatarUrl": "https://github.com/seeu100/blog/assets/138188931/f7f99053-8cce-4845-bed7-a0de9f8e3211", "GMEEK_VERSION": "last", "postListJson": {"P1": {"htmlDir": "docs/post/qian-yi-bo-ke-dao- github issues.html", "labels": ["\u8bb0\u5f55"], "postTitle": "\u8fc1\u79fb\u535a\u5ba2\u5230 github issues", "postUrl": "post/qian-yi-bo-ke-dao-%20github%20issues.html", "postSourceUrl": "https://github.com/seeu100/blog/issues/1", "commentNum": 1, "wordCount": 319, "description": "[Gmeek](https://github.com/Meekdai/Gmeek) \u4e00\u4e2a\u535a\u5ba2\u6846\u67b6\uff0c\u8d85\u8f7b\u91cf\u7ea7\u4e2a\u4eba\u535a\u5ba2\u6a21\u677f\uff0c\u5b8c\u5168\u57fa\u4e8e`Github Pages` \u3001 `Github Issues` \u548c `Github Actions`\uff0c\u53ef\u4ee5\u79f0\u4f5c`All in Github`\u3002\u4e0d\u9700\u8981\u672c\u5730\u90e8\u7f72\uff0c\u4ece\u642d\u5efa\u5230\u5199\u4f5c\uff0c\u53ea\u9700\u898118\u79d2\uff0c2\u6b65\u642d\u5efa\u597d\u535a\u5ba2\uff0c\u7b2c3\u6b65\u5c31\u662f\u5199\u4f5c\u3002\r\n\r\n[Gmeek\u5feb\u901f\u4e0a\u624b](https://blog.meekdai.com/post/Gmeek-kuai-su-shang-shou.html)\r\n[Issues \u00b7 Meekdai/Gmeek](https://github.com/Meekdai/Gmeek/issues)\r\n$$$$$$$", "top": 0, "createdAt": 1713412322, "style": "", "script": "", "createdDate": "2024-04-18", "dateLabelColor": "#bc4c00"}, "P2": {"htmlDir": "docs/post/tai-yang-xi-xing-xing-de-yan-se-yi-ji-ta-men-dui-ying-de-yan-se-dai-ma.html", "labels": ["\u8bb0\u5f55"], "postTitle": "\u592a\u9633\u7cfb\u884c\u661f\u7684\u989c\u8272\u4ee5\u53ca\u5b83\u4eec\u5bf9\u5e94\u7684\u989c\u8272\u4ee3\u7801", "postUrl": "post/tai-yang-xi-xing-xing-de-yan-se-yi-ji-ta-men-dui-ying-de-yan-se-dai-ma.html", "postSourceUrl": "https://github.com/seeu100/blog/issues/2", "commentNum": 1, "wordCount": 781, "description": "1. **\u6c34\u661f**\uff1a\u6c34\u661f\u8868\u9762\u7684\u989c\u8272\u56e0\u5149\u7167\u89d2\u5ea6\u4e0d\u540c\u800c\u53d8\u5316\uff0c\u6574\u4f53\u5448\u73b0\u51fa\u4e00\u79cd\u6697\u6de1\u7684\u7070\u8272\u81f3\u9ec4\u8910\u8272\uff0c\u63a5\u8fd1\u4e8e\u91d1\u9ec4\u8272\u6216\u8005\u6de1\u6a59\u8272\u3002\r\n   - \u989c\u8272\u4ee3\u7801\uff1a\u5927\u7ea6\u7c7b\u4f3c\u4e8e #DAA520\uff08\u6697\u91d1\u8272\uff09\u6216 #8B8682\uff08\u6697\u7070\u8272\uff09\u3002\r\n\r\n2. **\u91d1\u661f**\uff1a\u4ece\u5730\u7403\u4e0a\u770b\u5230\u7684\u91d1\u661f\u56e0\u4e3a\u6d53\u539a\u7684\u5927\u6c14\u5c42\u53cd\u5c04\u9633\u5149\uff0c\u5448\u73b0\u660e\u4eae\u7684\u767d\u8272\u6216\u91d1\u9ec4\u8272\u3002\r\n   - \u989c\u8272\u4ee3\u7801\uff1a\u63a5\u8fd1\u4e8e #FFFFCC\uff08\u6de1\u9ec4\u8272\uff09\u6216 #FFFFFF\uff08\u7eaf\u767d\u8272\uff09\u3002\r\n\r\n3. **\u5730\u7403**\uff1a\u7531\u4e8e\u6d77\u6d0b\u5360\u636e\u5927\u90e8\u5206\u9762\u79ef\uff0c\u5730\u7403\u4ece\u592a\u7a7a\u770b\u53bb\u5448\u73b0\u84dd\u8272\uff0c\u52a0\u4e0a\u9646\u5730\u7684\u7eff\u8272\u548c\u4e91\u5c42\u7684\u767d\u8272\u3002\r\n   - \u989c\u8272\u4ee3\u7801\uff1a\u4ee3\u8868\u6d77\u6d0b\u90e8\u5206\u7684 #00BFFF\uff08\u6df1\u5929\u84dd\uff09\uff1b\u603b\u4f53\u5916\u89c2\u53ef\u53c2\u8003 #00FFFF\uff08\u9752\u8272\uff09\u3002\r\n\r\n4. **\u706b\u661f**\uff1a\u706b\u661f\u56e0\u5176\u8868\u9762\u4e0a\u5bcc\u542b\u6c27\u5316\u94c1\uff08\u94c1\u9508\uff09\u800c\u5448\u73b0\u660e\u663e\u7684\u7ea2\u8272\u6216\u6697\u7ea2\u8272\u3002\r\n   - \u989c\u8272\u4ee3\u7801\uff1a #FF0000\uff08\u7ea2\u8272\uff09\u6216 #8B0000\uff08\u6df1\u7ea2\u8272\uff09\u3002\r\n\r\n5. **\u6728\u661f**\uff1a\u6728\u661f\u7684\u5927\u6c14\u5c42\u7531\u591a\u79cd\u6c14\u4f53\u7ec4\u6210\uff0c\u6574\u4f53\u770b\u8d77\u6765\u662f\u6de1\u9ec4\u8272\u7684\u80cc\u666f\u4e0a\u5e26\u6709\u660e\u663e\u7684\u6a59\u8272\u548c\u767d\u8272\u6761\u7eb9\u3002\r\n   - \u989c\u8272\u4ee3\u7801\uff1a\u5927\u81f4\u53ef\u8868\u793a\u4e3a #FDB813\uff08\u6d45\u91d1\u9ec4\u8272\uff09\u6216 #FFEBCD\uff08\u6de1\u7c73\u9ec4\u8272\uff09\u3002\r\n\r\n6. **\u571f\u661f**\uff1a\u571f\u661f\u5927\u6c14\u4e3b\u8981\u4e3a\u6c22\u548c\u6c26\uff0c\u4f46\u4e91\u5c42\u5e26\u5448\u73b0\u51fa\u4e0d\u540c\u7684\u8272\u5f69\uff0c\u5982\u91d1\u9ec4\u8272\u3001\u6a59\u8272\u548c\u68d5\u8272\uff0c\u4ee5\u53ca\u6781\u533a\u7684\u7eff\u8272\u533a\u57df\u3002\r\n   - \u989c\u8272\u4ee3\u7801\uff1a\u4e91\u5e26\u90e8\u5206\u53ef\u80fd\u662f #FFD700\uff08\u9ec4\u91d1\u8272\uff09\uff1b\u6574\u4e2a\u884c\u661f\u53ef\u89c6\u4e3a #C2B280\uff08\u6c99\u9ec4\u8272\uff09\u6216 #9ACD32\uff08\u6a44\u6984\u9ec4\u8272\uff09\u3002\r\n\r\n7. **\u5929\u738b\u661f**\uff1a\u5929\u738b\u661f\u7684\u5927\u6c14\u5c42\u4e3b\u8981\u662f\u6c22\u3001\u6c26\u548c\u7532\u70f7\uff0c\u5448\u73b0\u6de1\u6de1\u7684\u84dd\u8272\uff0c\u7c7b\u4f3c\u4e8e\u9e2d\u86cb\u58f3\u7684\u6d45\u7eff\u8272\u3002\r\n   - \u989c\u8272\u4ee3\u7801\uff1a #AAD6E6\uff08\u6de1\u84dd\u8272\uff09\u6216 #77DDDD\uff08\u6d45\u7eff\u8272\uff09\u3002\r\n\r\n8. **\u6d77\u738b\u661f**\uff1a\u6d77\u738b\u661f\u56e0\u4e3a\u5927\u6c14\u4e2d\u542b\u6709\u5927\u91cf\u7532\u70f7\u800c\u5448\u73b0\u51fa\u6df1\u6d77\u822c\u7684\u84dd\u8272\u3002\r\n   - \u989c\u8272\u4ee3\u7801\uff1a #0077BE\uff08\u6df1\u84dd\u8272\uff09\u6216 #5FA0D1\uff08\u4e2d\u84dd\u8272\uff09\u3002$$$$$$$", "top": 0, "createdAt": 1713428648, "style": "", "script": "", "createdDate": "2024-04-18", "dateLabelColor": "#bc4c00"}, "P3": {"htmlDir": "docs/post/13-ge-mian-fei-xia-zai- SVG -tu-biao-wang-zhan.html", "labels": ["\u8d44\u6e90"], "postTitle": "13\u4e2a\u514d\u8d39\u4e0b\u8f7d SVG \u56fe\u6807\u7f51\u7ad9", "postUrl": "post/13-ge-mian-fei-xia-zai-%20SVG%20-tu-biao-wang-zhan.html", "postSourceUrl": "https://github.com/seeu100/blog/issues/3", "commentNum": 0, "wordCount": 2524, "description": "[\u539f\u6587\u94fe\u63a5](https://blog.csdn.net/Me_Ordinary/article/details/108992807)\r\n\r\n\u5728\u524d\u7aef\u5f00\u53d1\u8fc7\u7a0b\u4e2d\uff0c\u7ecf\u5e38\u4f1a\u7528\u5230\u5404\u79cd\u56fe\u6807\u3002\u5728\u5404\u79cd\u56fe\u6807\u683c\u5f0f\u4e2d\uff0c\u56e0\u4e3a SVG \u65e2\u80fd\u6ee1\u8db3\u73b0\u6709\u56fe\u7247\u7684\u529f\u80fd\u7684\u524d\u63d0\u4e0b\uff0c\u53c8\u662f\u77e2\u91cf\u56fe\uff0c\u5728\u53ef\u8bbf\u95ee\u6027\u4e0a\u9762\u4e5f\u975e\u5e38\u4e0d\u9519\uff0c\u5e76\u4e14\u6709\u5229\u4e8e SEO \u548c\u65e0\u969c\u788d\uff0c\u5728\u6027\u80fd\u548c\u7ef4\u62a4\u6027\u65b9\u9762\u4e5f\u6bd4 iconfont \u8981\u51fa\u8272\u8bb8\u591a\uff0c\u662f\u76ee\u524d\u4f7f\u7528\u6700\u5e7f\u7684\u7c7b\u578b\uff0c\u4eca\u5929\u5c31\u7ed9\u5927\u5bb6\u4ecb\u7ecd\u4e00\u4e9b\u53ef\u4ee5\u514d\u8d39 SVG \u56fe\u6807\u7684\u7f51\u7ad9\u3002\r\n\r\n**1\u3001Ikonate**\r\n\r\nIkonate \u63d0\u4f9b200\u591a\u4e2a\u5b8c\u5168\u53ef\u5b9a\u5236\u7684\u77e2\u91cf\u56fe\u6807\u3002\u53ef\u4ee5\u968f\u610f\u8bbe\u7f6e\u56fe\u6807\u7684\u8fb9\u6846\u3001\u5927\u5c0f\u3001\u98ce\u683c\u3001\u989c\u8272\u7b49\u5c5e\u6027\u3002\u5728\u65e0\u969c\u788d\u6d4f\u89c8\u548c\u6027\u80fd\u65b9\u9762\u8be5\u5e93\u4e5f\u505a\u4e86\u5145\u8db3\u7684\u4f18\u5316\u3002\r\n\r\n\u7f51\u7ad9\u540d\u79f0\uff1aIkonate\r\n\u94fe\u63a5\u5730\u5740\uff1a[https://www.ikonate.com/](https://www.ikonate.com/)\r\n\r\n**2\u3001Simple Icons**\r\n\r\nSimple Icons \u6536\u5f55\u4e86\u70ed\u95e8\u7684\u54c1\u724cLogo\u7684SVG\u683c\u5f0f\uff0c\u540c\u65f6\u6839\u636e\u54c1\u724cLogo\u8bbe\u7f6e\u4e86\u80cc\u666f\u8272\uff0c\u65b9\u4fbf\u8bbe\u8ba1\u67e5\u627e\u3002\r\n\r\n\u7f51\u7ad9\u540d\u79f0\uff1aSimple Icons\r\n\u94fe\u63a5\u5730\u5740\uff1a[https://simpleicons.org](https://simpleicons.org/)\r\n\r\n**3\u3001SVG Icons**\r\n\r\nSVG Icons \u6536\u5f55\u7684\u56fe\u6807\u5168\u90e8\u6765\u81ea\u00a0[Dribbble](http://dribbble.com/)\u00a0\uff0c\u5168\u90e8\u53ef\u4ee5\u514d\u8d39\u4f7f\u7528\uff0c\u70b9\u51fb\u56fe\u6807\u6309\u94ae\u5373\u53ef\u5f39\u51fa\u56fe\u6807\u4ee3\u7801\uff0c\u975e\u5e38\u65b9\u4fbf\u3002\r\n\r\n\u7f51\u7ad9\u540d\u79f0\uff1aSVG Icons\r\n\u94fe\u63a5\u5730\u5740\uff1a[http://svgicons.sparkk.fr/](http://svgicons.sparkk.fr/)\r\n\r\n**4\u3001IconMonstr**\r\n\r\nIconMonstr \u662f\u4e00\u4e2a\u63d0\u4f9b\u514d\u8d39\u7684PNG/SVG\u683c\u5f0f\u7684\u7d20\u6750\u4e0b\u8f7d\u7ad9\u70b9\uff0c\u6536\u5f55\u4e864\u5343\u591a\u4e2a\u56fe\u6807\uff0c\u7528\u6237\u53ef\u4ee5\u641c\u7d22\u67e5\u627e\uff0c\u6240\u6709\u7d20\u6750\u90fd\u53ef\u4ee5\u514d\u8d39\u4e0b\u8f7d\u3002\r\n\r\n\u7f51\u7ad9\u540d\u79f0\uff1aIconMonstr\r\n\u94fe\u63a5\u5730\u5740\uff1a[https://iconmonstr.com/](https://iconmonstr.com/)\r\n\r\n**5\u3001ICONSVG**\r\n\r\nICONSVG \u662f\u4e00\u4e2a\u5728\u7ebf\u53ef\u81ea\u5b9a\u4e49\u8bbe\u8ba1SVG\u56fe\u6807\u7d20\u6750\u7684\u7f51\u7ad9\uff0c\u5e2e\u52a9\u524d\u7aef\u8bbe\u8ba1\u5e08\u627e\u5230\u60f3\u8981\u7684\u56fe\u6807\u7d20\u6750\uff0c\u8fd9\u4e9b\u56fe\u6807\u7d20\u6750\u90fd\u662f\u5e38\u7528\u56fe\u6807\uff0c\u53ef\u4ee5\u70b9\u51fb\u5b98\u65b9\u63d0\u4f9b\u7684\u7d20\u6750\u8fdb\u884c\u4e8c\u6b21\u8bbe\u8ba1\uff0c\u540c\u65f6\u4e5f\u53ef\u4ee5\u628a\u8bbe\u8ba1\u597d\u7684\u56fe\u6807\u5bfc\u51fa\u3002\r\n\r\n\u7f51\u7ad9\u540d\u79f0\uff1aICONSVG\r\n\u94fe\u63a5\u5730\u5740\uff1a[https://iconsvg.xyz/](https://iconsvg.xyz/)\r\n\r\n**6\u3001Feather Icons**\r\n\r\nFeather Icons \u662f\u4e00\u6b3e\u514d\u8d39\u3001\u5f00\u653e\u6e90\u4ee3\u7801\u7684\u77e2\u91cf\u56fe\u6807\u96c6\uff0c\u6536\u5f55\u516b\u5927\u7c7b\u578b\u5171233\u4e2a\u56fe\u6807\uff0c\u56fe\u6807\u8bbe\u8ba1\u572824\u00d724\u7f51\u683c\u4e0a\uff0c\u5728\u529f\u80fd\u3001\u4e00\u81f4\u6027\u3001\u7b80\u7ea6\u8bbe\u8ba1\u4e0a\u90fd\u5177\u6709\u76f8\u540c\u7279\u6027\uff0c\u56e0\u6b64\u5f88\u9002\u5408\u5728\u5f00\u53d1\u9879\u76ee\u4e2d\u4f7f\u7528\u3002\r\n\r\n\u7f51\u7ad9\u540d\u79f0\uff1aFeather Icons\r\n\u94fe\u63a5\u5730\u5740\uff1a[https://feathericons.com/](https://feathericons.com/)\r\n\r\n**7\u3001Flaticon**\r\n\r\nFlaticon \u6536\u5f55\u7684\u56fe\u6807\u90fd\u662f\u5355\u8272\u3001\u5e73\u9762\u5316\uff0c\u53ef\u4ee5\u9002\u7528\u4e8e\u4efb\u4f55\u7f51\u7ad9\u6216\u7528\u4e8e\u5546\u4e1a\u9879\u76ee\uff0c\u4f60\u53ef\u4ee5\u5f88\u65b9\u4fbf\u900f\u8fc7 CSS \u6216\u5176\u4ed6\u65b9\u5f0f\u6765\u91cd\u65b0\u8bbe\u8ba1\u56fe\u793a\uff0c\u8ba9\u5b83\u770b\u8d77\u6765\u66f4\u7b26\u5408\u4f60\u7684\u7f51\u7ad9\u3002\u4e5f\u53ef\u4ee5\u4e0b\u8f7d\u4e3a Webfont\u3001PNG \u6216\u662f SVG \u7b49\u683c\u5f0f\u3002\r\n\r\n\u7f51\u7ad9\u540d\u79f0\uff1aFlaticon\r\n\u94fe\u63a5\u5730\u5740\uff1a[https://www.flaticon.com/](https://www.flaticon.com/)\r\n\r\n**8\u3001Iconfont**\r\n\r\n\u56fd\u5185\u529f\u80fd\u5f88\u5f3a\u5927\u4e14\u56fe\u6807\u5185\u5bb9\u5f88\u4e30\u5bcc\u7684\u77e2\u91cf\u56fe\u6807\u5e93\uff0c\u63d0\u4f9b\u77e2\u91cf\u56fe\u6807\u4e0b\u8f7d\u3001\u5728\u7ebf\u5b58\u50a8\u3001\u683c\u5f0f\u8f6c\u6362\u7b49\u529f\u80fd\uff0c\u963f\u91cc\u5df4\u5df4\u4f53\u9a8c\u56e2\u961f\u503e\u529b\u6253\u9020\u3002\r\n\r\n\u7f51\u7ad9\u540d\u79f0\uff1aIconfont\r\n\u94fe\u63a5\u5730\u5740\uff1a[https://www.iconfont.cn/](https://www.iconfont.cn/)\r\n\r\n**9\u3001Evil Icons**\r\n\r\nEvil Icons \u662f\u4e00\u5957\u7b80\u5355\u5e72\u51c0\u7684SVG\u56fe\u6807\u96c6\uff0c\u5f00\u653e\u6e90\u4ee3\u7801\uff0c\u5bf9\u4e8e\u5f00\u53d1\u8005\u6765\u8bf4\u53ea\u8981\u51e0\u884c\u7a0b\u5f0f\u7801\u5c31\u80fd\u8f7b\u677e\u8c03\u7528\uff0c\u652f\u6301 Rails\u3001Sprockets\u3001Node.js\u3001Gulp\u3001Grunt \u548c CDN\uff0c\u5982\u679c\u60f3\u8981\u81ea\u5df1\u4fee\u6539\u6216\u91cd\u65b0\u8bbe\u8ba1\uff0cEvil Icons \u8fd8\u63d0\u4f9b SVG\u3001AI \u53ca Sketch \u56fe\u6807\u683c\u5f0f\u4e0b\u8f7d\u3002\r\n\r\n\u7f51\u7ad9\u540d\u79f0\uff1aEvil Icons\r\n\u94fe\u63a5\u5730\u5740\uff1a[https://evil-icons.io/](https://evil-icons.io/)\r\n\r\n**10\u3001Icons8**\r\n\r\nIcons8 \u4e3b\u8981\u4ee5\u63d0\u4f9b\u514d\u8d39\u7684\u5e73\u9762\u5316\u8bbe\u8ba1\u56fe\u6807\u4e3a\u4e3b\uff0c\u53ef\u6839\u636e\u4e0d\u540c\u5e73\u53f0\u7684\u8bbe\u8ba1\u98ce\u683c\u6765\u7b5b\u9009\u3002\r\n\r\n\u7f51\u7ad9\u540d\u79f0\uff1aIcons8\r\n\u94fe\u63a5\u5730\u5740\uff1a[https://icons8.com](https://icons8.com/)\r\n\r\n**11\u3001Free icons**\r\n\r\nFree icons\u662f\u4e00\u4e2a\u53ef\u4ee5\u514d\u8d39\u4e0b\u8f7dSVG\u3001PNG\u3001EPS\u3001AI\u548cPSD\u683c\u5f0f\u7684\u5e73\u53f0\uff0c\u5728\u8fd9\u91cc\uff0c\u53ef\u4ee5\u627e\u5230\u5404\u79cd\u4e0d\u540c\u6837\u5f0f\u3001\u5927\u5c0f\u3001\u683c\u5f0f\u548c\u4e3b\u9898\u7684\u56fe\u6807\u3002\u6240\u6709\u8fd9\u4e9b\u56fe\u6807\u5b8c\u5168\u514d\u8d39\u4f9b\u4e2a\u4eba\u548c\u5546\u4e1a\u4f7f\u7528\u3002\r\n\r\n\u7f51\u7ad9\u540d\u79f0\uff1aFree icons\r\n\u94fe\u63a5\u5730\u5740\uff1a[https://freeicons.io](https://freeicons.io/)\r\n\r\n**12\u3001illustrio**\r\n\r\nillustrio \u4e0d\u4ec5\u7d20\u6750\u5e93\u5168\u9762\uff0c\u8fd8\u53ef\u4ee5\u5728\u7ebf\u81ea\u5b9a\u4e49\u914d\u8272\u9884\u89c8\u5b9a\u5236\u7684 15 \u79cd\u4e0d\u540c\u98ce\u683c\uff0c\u5982\u679c\u662f\u521d\u6b21\u4f7f\u7528\uff0c\u4e0b\u8f7d\u524d\u9700\u5148\u4f7f\u7528\u90ae\u7bb1\u6ce8\u518c\u4e00\u4e2a\u8d26\u6237\u5e76\u5728\u90ae\u7bb1\u4e2d\u786e\u8ba4\u3002\r\n\r\n\u7f51\u7ad9\u540d\u79f0\uff1aillustrio\r\n\u94fe\u63a5\u5730\u5740\uff1a[https://illustrio.com](https://illustrio.com/)\r\n\r\n**13\u3001Easyicon**\r\n\r\n\u56fd\u5185\u5f00\u53d1\u8005\uff0c\u63d0\u4f9b\u2605\u8d85\u8fc7\u516d\u5341\u4e07\u4e2a\u2605SVG\u3001PNG\u3001ICO\u3001ICNS\u56fe\u6807\u641c\u7d22\u3001\u56fe\u6807\u4e0b\u8f7d\u670d\u52a1\u3002\r\n\r\n\u7f51\u7ad9\u540d\u79f0\uff1aEasyicon\r\n\u94fe\u63a5\u5730\u5740\uff1a[https://www.easyicon.net/](https://www.easyicon.net/)$$$$$$$", "top": 0, "createdAt": 1713433592, "style": "", "script": "", "createdDate": "2024-04-18", "dateLabelColor": "#bc4c00"}, "P5": {"htmlDir": "docs/post/shua-ji-gong-ju--adb\u3001fastboot.html", "labels": ["\u8f6f\u4ef6"], "postTitle": "\u5237\u673a\u5de5\u5177-adb\u3001fastboot", "postUrl": "post/shua-ji-gong-ju--adb%E3%80%81fastboot.html", "postSourceUrl": "https://github.com/seeu100/blog/issues/5", "commentNum": 0, "wordCount": 263, "description": "\u4e0b\u8f7d\u5730\u5740\u5982\u4e0b\uff1a\r\n\r\n- https://dl.google.com/android/repository/platform-tools-latest-darwin.zip\r\n- https://dl.google.com/android/repository/platform-tools-latest-linux.zip\r\n- https://dl.google.com/android/repository/platform-tools-latest-windows.zip\r\n\r\n\u4ece\u6b64\u5730\u5740\u4e0b\u8f7d\u7684\u5de5\u5177\u5305\u5c06\u6c38\u8fdc\u662f\u6700\u65b0\u7248\u672c\u3002$$$$$$$", "top": 0, "createdAt": 1713434256, "style": "", "script": "", "createdDate": "2024-04-18", "dateLabelColor": "#bc4c00"}}, "singeListJson": {"P4": {"htmlDir": "docs/about.html", "labels": ["about"], "postTitle": "\u5173\u4e8e", "postUrl": "about.html", "postSourceUrl": "https://github.com/seeu100/blog/issues/4", "commentNum": 0, "wordCount": 326, "description": "> \u6211\u5c31\u50cf\u4e00\u6ef4\u5927\u6d77\u4e2d\u7684\u6c34\uff0c\u5927\u5343\u4e16\u754c\u7684\u4e00\u4e2a\u7535\u5b50\uff0c\u54ea\u91cc\u90fd\u6709\u6211\uff0c\u54ea\u91cc\u90fd\u6ca1\u6709\u6211\u3002\r\n\r\n## \u6211\u7684\u6280\u80fd\r\n\r\n- Linux\uff1a\u65e5\u5e38\u4f7f\u7528\u3001\u5185\u6838\u7f16\u8bd1\u3001\u73af\u5883\u642d\u5efa\u3001Docker\r\n- \u7f51\u7ad9\u642d\u5efa\uff1aNgnix\u3001DNS\u89e3\u6790\u3001Hugo\u3001Github Pages\r\n- \u57fa\u56e0\u7ec4\u7ec4\u88c5\u6ce8\u91ca\r\n- \u7cfb\u7edf\u53d1\u80b2\u5efa\u6811\r\n\r\n\u534a\u6876\u6c34\u6280\u80fd\uff1a\r\n- [ ] Shell \u7f16\u7a0b\r\n- [ ] Python\r\n- [ ] R\r\n- [ ] Rust\r\n- [ ] ruby\r\n- [ ] C\r\n- [ ] Openwrt\r\n- [ ] Android\r\n- [ ] Java\r\n- [ ] javascript\r\n\r\n## \u6211\u7684\u7ecf\u5386\r\n\r\n- [ ] 2021-2024 \u5341\u5927\u529f\u52b3\u5c5e\u7684\u5206\u7c7b\u4fee\u8ba2\r\n\r\n$$$$$$$", "top": 0, "createdAt": 1713433908, "style": "", "script": "", "createdDate": "2024-04-18", "dateLabelColor": "#bc4c00"}}, "labelColorDict": {"Linux": "#CD45CE", "\u8bb0\u5f55": "#82B371"}, "displayTitle": "\u4e00\u767e\u5e74\u540e\u518d\u89c1", "faviconUrl": "https://github.com/seeu100/blog/assets/138188931/f7f99053-8cce-4845-bed7-a0de9f8e3211", "prevUrl": "disabled", "nextUrl": "disabled"}